{"nodes": [{"id": "login", "label": "Login.tsx", "file_type": "code", "source_file": "src/pages/Login.tsx", "source_location": "L1"}, {"id": "login_login", "label": "Login()", "file_type": "code", "source_file": "src/pages/Login.tsx", "source_location": "L9"}], "edges": [{"source": "login", "target": "react", "relation": "imports_from", "confidence": "EXTRACTED", "source_file": "src/pages/Login.tsx", "source_location": "L1", "weight": 1.0}, {"source": "login", "target": "wouter", "relation": "imports_from", "confidence": "EXTRACTED", "source_file": "src/pages/Login.tsx", "source_location": "L2", "weight": 1.0}, {"source": "login", "target": "useauth", "relation": "imports_from", "confidence": "EXTRACTED", "source_file": "src/pages/Login.tsx", "source_location": "L3", "weight": 1.0}, {"source": "login", "target": "button", "relation": "imports_from", "confidence": "EXTRACTED", "source_file": "src/pages/Login.tsx", "source_location": "L4", "weight": 1.0}, {"source": "login", "target": "input", "relation": "imports_from", "confidence": "EXTRACTED", "source_file": "src/pages/Login.tsx", "source_location": "L5", "weight": 1.0}, {"source": "login", "target": "label", "relation": "imports_from", "confidence": "EXTRACTED", "source_file": "src/pages/Login.tsx", "source_location": "L6", "weight": 1.0}, {"source": "login", "target": "lucide_react", "relation": "imports_from", "confidence": "EXTRACTED", "source_file": "src/pages/Login.tsx", "source_location": "L7", "weight": 1.0}, {"source": "login", "target": "login_login", "relation": "contains", "confidence": "EXTRACTED", "source_file": "src/pages/Login.tsx", "source_location": "L9", "weight": 1.0}]}